braincube_token_getter/__init__.py
braincube_token_getter/script.py
braincube_token_getter-0.0.2.dist-info/entry_points.txt
braincube_token_getter-0.0.2.dist-info/WHEEL
braincube_token_getter-0.0.2.dist-info/METADATA
braincube_token_getter-0.0.2.dist-info/RECORD
