Metadata-Version: 2.1
Name: braincube-token-getter
Version: 0.0.2
Summary: A utility to get a braincube token
License: MIT
Keywords: bc_connector,braincube_connector,braincube,token
Author: Braincube
Author-email: io@braincube.com
Requires-Python: >=3.6,<4.0
Classifier: Framework :: Flask
Classifier: License :: OSI Approved :: MIT License
Classifier: Operating System :: OS Independent
Classifier: Programming Language :: Python :: 3
Classifier: Programming Language :: Python :: 3.6
Classifier: Programming Language :: Python :: 3.7
Classifier: Programming Language :: Python :: 3.8
Requires-Dist: Flask (>=1.1.2,<2.0.0)
Requires-Dist: pyopenssl (>=19.1.0,<20.0.0)
Requires-Dist: requests (>=2.23.0,<3.0.0)
